Workbook
Name Clients: Client_dim!$B$1:$C$29

Sheet Revenue_Fact
A1: TRANS_ID | B1: Date | C1: Client_ID | D1: Departmnet_ID | E1: State_ID | F1: Payment_ID | G1: Revenue | H1: Profit | I1: Profit Margin
A2: T-101 | B2: 45076 | C2: C101 | D2: D-102 | E2: S-104 | F2: P-105 | G2: 4500 | H2: 598 | I2: =IFERROR(H2/B8,0) -> 0.013266189
A3: T-102 | B3: 45076 | C3: C123 | D3: D-104 | E3: S-103 | F3: P-104 | G3: 3800 | H3: 1045 | I3: =IFERROR(H3/B9,0) -> 0.023182554
A4: T-103 | B4: 45076 | C4: C121 | D4: D-104 | E4: S-103 | F4: P-103 | G4: 3712.5 | H4: 1009 | I4: =IFERROR(H4/B10,0) -> 0.022383921
A5: T-104 | B5: 45076 | C5: C126 | D5: D-103 | E5: S-102 | F5: P-103 | G5: =4994 -> 4994 | H5: 779 | I5: =IFERROR(H5/B11,0) -> 0.01728154
A6: T-105 | B6: 45076 | C6: C124 | D6: D-103 | E6: S-102 | F6: P-102 | G6: 5000 | H6: 684 | I6: =IFERROR(H6/B12,0) -> 0.015174036
A7: T-106 | B7: 45077 | C7: C116 | D7: D-102 | E7: S-104 | F7: P-105 | G7: 6100 | H7: 544 | I7: =IFERROR(H7/B13,0) -> 0.012068239
A8: T-107 | B8: 45077 | C8: C120 | D8: D-102 | E8: S-104 | F8: P-105 | G8: 4625 | H8: 670 | I8: =IFERROR(H8/B14,0) -> 0.014863456
A9: T-108 | B9: 45077 | C9: C106 | D9: D-102 | E9: S-104 | F9: P-105 | G9: =5039 -> 5039 | H9: 2045 | I9: =IFERROR(H9/B15,0) -> 0.04536581
A10: T-109 | B10: 45077 | C10: C103 | D10: D-102 | E10: S-104 | F10: P-101 | G10: 3600 | H10: 1564 | I10: =IFERROR(H10/B16,0) -> 0.034695417
A11: T-110 | B11: 45077 | C11: C128 | D11: D-102 | E11: S-104 | F11: P-102 | G11: 5100 | H11: 1220 | I11: =IFERROR(H11/B17,0) -> 0.0270642
A12: T-111 | B12: 45077 | C12: C122 | D12: D-102 | E12: S-104 | F12: P-102 | G12: 4750 | H12: 1435 | I12: =IFERROR(H12/B18,0) -> 0.03183371
A13: T-112 | B13: 45077 | C13: C108 | D13: D-103 | E13: S-102 | F13: P-105 | G13: 6000 | H13: 998 | I13: =IFERROR(H13/B19,0) -> 0.022139403
A14: T-113 | B14: 45077 | C14: C118 | D14: D-101 | E14: S-101 | F14: P-102 | G14: =5039 -> 5039 | H14: 780 | I14: =IFERROR(H14/B20,0) -> 0.017303341
A15: T-114 | B15: 45078 | C15: C110 | D15: D-101 | E15: S-101 | F15: P-101 | G15: =4994 -> 4994 | H15: 1044 | I15: =IFERROR(H15/B21,0) -> 0.023159856
A16: T-115 | B16: 45078 | C16: C127 | D16: D-101 | E16: S-101 | F16: P-105 | G16: 3712.5 | H16: 1222 | I16: =IFERROR(H16/B22,0) -> 0.027108567
A17: T-116 | B17: 45078 | C17: C125 | D17: D-101 | E17: S-101 | F17: P-105 | G17: 4950 | H17: 1065 | I17: =IFERROR(H17/B23,0) -> 0.023625191
A18: T-117 | B18: 45078 | C18: C105 | D18: D-103 | E18: S-102 | F18: P-105 | G18: 4750 | H18: 810 | I18: =IFERROR(H18/B24,0) -> 0.017968455
A19: T-118 | B19: 45078 | C19: C104 | D19: D-103 | E19: S-102 | F19: P-105 | G19: 7320 | H19: 933 | I19: =IFERROR(H19/B25,0) -> 0.020696999
A20: T-119 | B20: 45078 | C20: C102 | D20: D-101 | E20: S-101 | F20: P-105 | G20: 5087.5 | H20: 655 | I20: =IFERROR(H20/B26,0) -> 0.014530047
A21: T-120 | B21: 45078 | C21: C114 | D21: D-101 | E21: S-101 | F21: P-105 | G21: 4500 | H21: 722 | I21: =IFERROR(H21/B27,0) -> 0.016016327
A22: T-121 | B22: 45078 | C22: C113 | D22: D-101 | E22: S-101 | F22: P-101 | G22: 4250 | H22: 901 | I22: =IFERROR(H22/B28,0) -> 0.019987134
A23: T-122 | B23: 45079 | C23: C119 | D23: D-101 | E23: S-101 | F23: P-104 | G23: 5250 | H23: 1349 | I23: =IFERROR(H23/B29,0) -> 0.029925242
A24: T-123 | B24: 45079 | C24: C107 | D24: D-104 | E24: S-103 | F24: P-104 | G24: 6500 | H24: 1288 | I24: =IFERROR(H24/#REF!,0) -> 0
A25: T-124 | B25: 45079 | C25: C109 | D25: D-104 | E25: S-103 | F25: P-104 | G25: 7500 | H25: 1664 | I25: =IFERROR(H25/B31,0) -> 0
A26: T-125 | B26: 45079 | C26: C115 | D26: D-104 | E26: S-103 | F26: P-105 | G26: 5500 | H26: 1320 | I26: =IFERROR(H26/B32,0) -> 0
A27: T-126 | B27: 45079 | C27: C111 | D27: D-104 | E27: S-103 | F27: P-105 | G27: 4625 | H27: 1001 | I27: =IFERROR(H27/B33,0) -> 0
A28: T-127 | B28: 45079 | C28: C112 | D28: D-104 | E28: S-103 | F28: P-105 | G28: 4500 | H28: 960 | I28: =IFERROR(H28/B34,0) -> 0
A29: T-128 | B29: 45079 | C29: C117 | D29: D-104 | E29: S-103 | F29: P-101 | G29: 5400 | H29: 540 | I29: =IFERROR(H29/B35,0) -> 0
A30: T-129 | B30: 45080 | C30: C118 | D30: D-105 | E30: S-104 | F30: P-102 | G30: 5400 | H30: 540 | I30: =IFERROR(H30/B36,0) -> 0

Sheet Client_dim
A1: Client | B1: Client_ID | C1: Client2 | D1: Contacts
A2: AMAZON.COM, INC. | B2: C101 | C2: AMAZON.COM, INC. | D2: Bill Smith
A3: AT&T INC. | B3: C102 | C3: AT&T INC. | D3: Bruno Cordova
A4: BANK OF AMERICA CORPORATION | B4: C103 | C4: BANK OF AMERICA CORPORATION | D4: Kylee Townsend
A5: CHEVRON CORPORATION | B5: C104 | C5: CHEVRON CORPORATION | D5: Denzel Flores
A6: CISCO SYSTEMS, INC. | B6: C105 | C6: CISCO SYSTEMS, INC. | D6: Alia Thornton
A7: CITIGROUP INC. | B7: C106 | C7: CITIGROUP INC. | D7: Jordan Boone
A8: COMCAST CORPORATION | B8: C107 | C8: COMCAST CORPORATION | D8: Bryce Carpenter
A9: COSTCO WHOLESALE CORPORATION | B9: C108 | C9: COSTCO WHOLESALE CORPORATION | D9: Conor Wise
A10: DELL TECHNOLOGIES INC. | B10: C109 | C10: DELL TECHNOLOGIES INC. | D10: Jaidyn Andersen
A11: EXXON MOBIL CORPORATION | B11: C110 | C11: EXXON MOBIL CORPORATION | D11: Lucia Mckay
A12: FEDEX CORPORATION | B12: C111 | C12: FEDEX CORPORATION | D12: Harry Lee
... A29: WALMART INC. | B29: C128 | C29: WALMART INC. | D29: Nora Rollins

Sheet Department_dim
A1: Department | B1: Department_ID
A2: Big Data | B2: D-101
A3: Cloud Tech | B3: D-102
A4: Operations | B4: D-103
A5: Strategy | B5: D-104

Sheet State_dim
A1: State | B1: State_ID
A2: California | B2: S-101
A3: Florida | B3: S-102
A4: New York | B4: S-103
A5: Texas | B5: S-104

Sheet Payment_dim
A1: Payment | B1: Payment_ID
A2: Card | B2: P-101
A3: Check | B3: P-102
A4: Others | B4: P-103
A5: PayPal | B5: P-104
A6: Transfer | B6: P-105

Sheet  RevenueVLOOOKUP
B1: CS101
A2: TRANS_ID | B2: Date | C2: Client_ID | D2: Client | E2: Department_ID | F2: Department | G2: State_ID | H2: State | I2: Payment_ID | J2: Payment | K2: Revenue | L2: Profit | M2: Profit Margin
A3: T-101 | B3: 45076 | C3: =VLOOKUP(D3,Client_dim!$A$2:$B$29,2,0) -> C101 | D3: AMAZON.COM, INC. | E3: =VLOOKUP(F3,Department_dim!A$1:B$5,2,FALSE) -> D-102 | F3: Cloud Tech | G3: =VLOOKUP(H3,State_dim!A$1:B$5,2,0) -> S-104 | H3: Texas | I3: =VLOOKUP(J3,Payment_dim!A$1:B$6,2,0) -> P-105 | J3: Transfer | K3: 4500 | L3: 598 | M3: =IFERROR(L3/K3,0) -> 0.13288889
A4: T-102 | B4: 45076 | C4: =VLOOKUP(D4,Client_dim!$A$2:$B$29,2,0) -> C123 | D4: TESLA, INC. | E4: =VLOOKUP(F4,Department_dim!A$1:B$5,2,FALSE) -> D-104 | F4: Strategy | G4: =VLOOKUP(H4,State_dim!A$1:B$5,2,0) -> S-103 | H4: New York | I4: =VLOOKUP(J4,Payment_dim!A$1:B$6,2,0) -> P-104 | J4: PayPal | K4: 3800 | L4: 1045 | M4: =IFERROR(L4/K4,0) -> 0.275
A5: T-103 | B5: 45076 | C5: =VLOOKUP(D5,Client_dim!$A$2:$B$29,2,0) -> C121 | D5: NETFLIX, INC. | E5: =VLOOKUP(F5,Department_dim!A$1:B$5,2,FALSE) -> D-104 | F5: Strategy | G5: =VLOOKUP(H5,State_dim!A$1:B$5,2,0) -> S-103 | H5: New York | I5: =VLOOKUP(J5,Payment_dim!A$1:B$6,2,0) -> P-103 | J5: Others | K5: 3712.5 | L5: 1009 | M5: =IFERROR(L5/K5,0) -> 0.27178451
A6: T-104 | B6: 45076 | C6: =VLOOKUP(D6,Client_dim!$A$2:$B$29,2,0) -> C126 | D6: THE PROCTER & GAMBLE COMPANY | E6: =VLOOKUP(F6,Department_dim!A$1:B$5,2,FALSE) -> D-103 | F6: Operations | G6: =VLOOKUP(H6,State_dim!A$1:B$5,2,0) -> S-102 | H6: Florida | I6: =VLOOKUP(J6,Payment_dim!A$1:B$6,2,0) -> P-103 | J6: Others | K6: =4994 -> 4994 | L6: 779 | M6: =IFERROR(L6/K6,0) -> 0.15598718
A7: T-105 | B7: 45076 | C7: =VLOOKUP(D7,Client_dim!$A$2:$B$29,2,0) -> C124 | D7: THE GOLDMAN SACHS GROUP, INC. | E7: =VLOOKUP(F7,Department_dim!A$1:B$5,2,FALSE) -> D-103 | F7: Operations | G7: =VLOOKUP(H7,State_dim!A$1:B$5,2,0) -> S-102 | H7: Florida | I7: =VLOOKUP(J7,Payment_dim!A$1:B$6,2,0) -> P-102 | J7: Check | K7: 5000 | L7: 684 | M7: =IFERROR(L7/K7,0) -> 0.1368
A8: T-106 | B8: 45077 | C8: =VLOOKUP(D8,Client_dim!$A$2:$B$29,2,0) -> C116 | D8: JPMORGAN CHASE & CO. | E8: =VLOOKUP(F8,Department_dim!A$1:B$5,2,FALSE) -> D-102 | F8: Cloud Tech | G8: =VLOOKUP(H8,State_dim!A$1:B$5,2,0) -> S-104 | H8: Texas | I8: =VLOOKUP(J8,Payment_dim!A$1:B$6,2,0) -> P-105 | J8: Transfer | K8: 6100 | L8: 544 | M8: =IFERROR(L8/K8,0) -> 0.089180328
A9: T-107 | B9: 45077 | C9: =VLOOKUP(D9,Client_dim!$A$2:$B$29,2,0) -> C120 | D9: MORGAN STANLEY | E9: =VLOOKUP(F9,Department_dim!A$1:B$5,2,FALSE) -> D-102 | F9: Cloud Tech | G9: =VLOOKUP(H9,State_dim!A$1:B$5,2,0) -> S-104 | H9: Texas | I9: =VLOOKUP(J9,Payment_dim!A$1:B$6,2,0) -> P-105 | J9: Transfer | K9: 4625 | L9: 670 | M9: =IFERROR(L9/K9,0) -> 0.14486486
A10: T-108 | B10: 45077 | C10: =VLOOKUP(D10,Client_dim!$A$2:$B$29,2,0) -> C106 | D10: CITIGROUP INC. | E10: =VLOOKUP(F10,Department_dim!A$1:B$5,2,FALSE) -> D-102 | F10: Cloud Tech | G10: =VLOOKUP(H10,State_dim!A$1:B$5,2,0) -> S-104 | H10: Texas | I10: =VLOOKUP(J10,Payment_dim!A$1:B$6,2,0) -> P-105 | J10: Transfer | K10: =5039 -> 5039 | L10: 2045 | M10: =IFERROR(L10/K10,0) -> 0.40583449
A11: T-109 | B11: 45077 | C11: =VLOOKUP(D11,Client_dim!$A$2:$B$29,2,0) -> C103 | D11: BANK OF AMERICA CORPORATION | E11: =VLOOKUP(F11,Department_dim!A$1:B$5,2,FALSE) -> D-102 | F11: Cloud Tech | G11: =VLOOKUP(H11,State_dim!A$1:B$5,2,0) -> S-104 | H11: Texas | I11: =VLOOKUP(J11,Payment_dim!A$1:B$6,2,0) -> P-101 | J11: Card | K11: 3600 | L11: 1564 | M11: =IFERROR(L11/K11,0) -> 0.43444444
A12: T-110 | B12: 45077 | C12: =VLOOKUP(D12,Client_dim!$A$2:$B$29,2,0) -> C128 | D12: WALMART INC. | E12: =VLOOKUP(F12,Department_dim!A$1:B$5,2,FALSE) -> D-102 | F12: Cloud Tech | G12: =VLOOKUP(H12,State_dim!A$1:B$5,2,0) -> S-104 | H12: Texas | I12: =VLOOKUP(J12,Payment_dim!A$1:B$6,2,0) -> P-102 | J12: Check | K12: 5100 | L12: 1220 | M12: =IFERROR(L12/K12,0) -> 0.23921569
A13: T-111 | B13: 45077 | C13: =VLOOKUP(D13,Client_dim!$A$2:$B$29,2,0) -> C122 | D13: TARGET CORPORATION | E13: =VLOOKUP(F13,Department_dim!A$1:B$5,2,FALSE) -> D-102 | F13: Cloud Tech | G13: =VLOOKUP(H13,State_dim!A$1:B$5,2,0) -> S-104 | H13: Texas | I13: =VLOOKUP(J13,Payment_dim!A$1:B$6,2,0) -> P-102 | J13: Check | K13: 4750 | L13: 1435 | M13: =IFERROR(L13/K13,0) -> 0.30210526
A14: T-112 | B14: 45077 | C14: =VLOOKUP(D14,Client_dim!$A$2:$B$29,2,0) -> C108 | D14: COSTCO WHOLESALE CORPORATION | E14: =VLOOKUP(F14,Department_dim!A$1:B$5,2,FALSE) -> D-103 | F14: Operations | G14: =VLOOKUP(H14,State_dim!A$1:B$5,2,0) -> S-102 | H14: Florida | I14: =VLOOKUP(J14,Payment_dim!A$1:B$6,2,0) -> P-105 | J14: Transfer | K14: 6000 | L14: 998 | M14: =IFERROR(L14/K14,0) -> 0.16633333
A15: T-113 | B15: 45077 | C15: =VLOOKUP(D15,Client_dim!$A$2:$B$29,2,0) -> C118 | D15: MCDONALD'S CORPORATION | E15: =VLOOKUP(F15,Department_dim!A$1:B$5,2,FALSE) -> D-101 | F15: Big Data | G15: =VLOOKUP(H15,State_dim!A$1:B$5,2,0) -> S-101 | H15: California | I15: =VLOOKUP(J15,Payment_dim!A$1:B$6,2,0) -> P-102 | J15: Check | K15: =5039 -> 5039 | L15: 780 | M15: =IFERROR(L15/K15,0) -> 0.15479262
A16: T-114 | B16: 45078 | C16: =VLOOKUP(D16,Client_dim!$A$2:$B$29,2,0) -> C110 | D16: EXXON MOBIL CORPORATION | E16: =VLOOKUP(F16,Department_dim!A$1:B$5,2,FALSE) -> D-101 | F16: Big Data | G16: =VLOOKUP(H16,State_dim!A$1:B$5,2,0) -> S-101 | H16: California | I16: =VLOOKUP(J16,Payment_dim!A$1:B$6,2,0) -> P-101 | J16: Card | K16: =4994 -> 4994 | L16: 1044 | M16: =IFERROR(L16/K16,0) -> 0.20905086
A17: T-115 | B17: 45078 | C17: =VLOOKUP(D17,Client_dim!$A$2:$B$29,2,0) -> C127 | D17: VERIZON COMMUNICATIONS INC. | E17: =VLOOKUP(F17,Department_dim!A$1:B$5,2,FALSE) -> D-101 | F17: Big Data | G17: =VLOOKUP(H17,State_dim!A$1:B$5,2,0) -> S-101 | H17: California | I17: =VLOOKUP(J17,Payment_dim!A$1:B$6,2,0) -> P-105 | J17: Transfer | K17: 3712.5 | L17: 1222 | M17: =IFERROR(L17/K17,0) -> 0.32915825
A18: T-116 | B18: 45078 | C18: =VLOOKUP(D18,Client_dim!$A$2:$B$29,2,0) -> C125 | D18: THE HOME DEPOT, INC. | E18: =VLOOKUP(F18,Department_dim!A$1:B$5,2,FALSE) -> D-101 | F18: Big Data | G18: =VLOOKUP(H18,State_dim!A$1:B$5,2,0) -> S-101 | H18: California | I18: =VLOOKUP(J18,Payment_dim!A$1:B$6,2,0) -> P-105 | J18: Transfer | K18: 4950 | L18: 1065 | M18: =IFERROR(L18/K18,0) -> 0.21515152
A19: T-117 | B19: 45078 | C19: =VLOOKUP(D19,Client_dim!$A$2:$B$29,2,0) -> C105 | D19: CISCO SYSTEMS, INC. | E19: =VLOOKUP(F19,Department_dim!A$1:B$5,2,FALSE) -> D-103 | F19: Operations | G19: =VLOOKUP(H19,State_dim!A$1:B$5,2,0) -> S-102 | H19: Florida | I19: =VLOOKUP(J19,Payment_dim!A$1:B$6,2,0) -> P-105 | J19: Transfer | K19: 4750 | L19: 810 | M19: =IFERROR(L19/K19,0) -> 0.17052632
A20: T-118 | B20: 45078 | C20: =VLOOKUP(D20,Client_dim!$A$2:$B$29,2,0) -> C104 | D20: CHEVRON CORPORATION | E20: =VLOOKUP(F20,Department_dim!A$1:B$5,2,FALSE) -> D-103 | F20: Operations | G20: =VLOOKUP(H20,State_dim!A$1:B$5,2,0) -> S-102 | H20: Florida | I20: =VLOOKUP(J20,Payment_dim!A$1:B$6,2,0) -> P-105 | J20: Transfer | K20: 7320 | L20: 933 | M20: =IFERROR(L20/K20,0) -> 0.12745902
A21: T-119 | B21: 45078 | C21: =VLOOKUP(D21,Client_dim!$A$2:$B$29,2,0) -> C102 | D21: AT&T INC. | E21: =VLOOKUP(F21,Department_dim!A$1:B$5,2,FALSE) -> D-101 | F21: Big Data | G21: =VLOOKUP(H21,State_dim!A$1:B$5,2,0) -> S-101 | H21: California | I21: =VLOOKUP(J21,Payment_dim!A$1:B$6,2,0) -> P-105 | J21: Transfer | K21: 5087.5 | L21: 655 | M21: =IFERROR(L21/K21,0) -> 0.12874693
A22: T-120 | B22: 45078 | C22: =VLOOKUP(D22,Client_dim!$A$2:$B$29,2,0) -> C114 | D22: INTEL CORPORATION | E22: =VLOOKUP(F22,Department_dim!A$1:B$5,2,FALSE) -> D-101 | F22: Big Data | G22: =VLOOKUP(H22,State_dim!A$1:B$5,2,0) -> S-101 | H22: California | I22: =VLOOKUP(J22,Payment_dim!A$1:B$6,2,0) -> P-105 | J22: Transfer | K22: 4500 | L22: 722 | M22: =IFERROR(L22/K22,0) -> 0.16044444
A23: T-121 | B23: 45078 | C23: =VLOOKUP(D23,Client_dim!$A$2:$B$29,2,0) -> C113 | D23: GENERAL MOTORS COMPANY | E23: =VLOOKUP(F23,Department_dim!A$1:B$5,2,FALSE) -> D-101 | F23: Big Data | G23: =VLOOKUP(H23,State_dim!A$1:B$5,2,0) -> S-101 | H23: California | I23: =VLOOKUP(J23,Payment_dim!A$1:B$6,2,0) -> P-101 | J23: Card | K23: 4250 | L23: 901 | M23: =IFERROR(L23/K23,0) -> 0.212
A24: T-122 | B24: 45079 | C24: =VLOOKUP(D24,Client_dim!$A$2:$B$29,2,0) -> C119 | D24: MICROSOFT CORPORATION | E24: =VLOOKUP(F24,Department_dim!A$1:B$5,2,FALSE) -> D-101 | F24: Big Data | G24: =VLOOKUP(H24,State_dim!A$1:B$5,2,0) -> S-101 | H24: California | I24: =VLOOKUP(J24,Payment_dim!A$1:B$6,2,0) -> P-104 | J24: PayPal | K24: 5250 | L24: 1349 | M24: =IFERROR(L24/K24,0) -> 0.25695238
A25: T-123 | B25: 45079 | C25: =VLOOKUP(D25,Client_dim!$A$2:$B$29,2,0) -> C107 | D25: COMCAST CORPORATION | E25: =VLOOKUP(F25,Department_dim!A$1:B$5,2,FALSE) -> D-104 | F25: Strategy | G25: =VLOOKUP(H25,State_dim!A$1:B$5,2,0) -> S-103 | H25: New York | I25: =VLOOKUP(J25,Payment_dim!A$1:B$6,2,0) -> P-104 | J25: PayPal | K25: 6500 | L25: 1288 | M25: =IFERROR(L25/K25,0) -> 0.19815385
A26: T-124 | B26: 45079 | C26: =VLOOKUP(D26,Client_dim!$A$2:$B$29,2,0) -> C109 | D26: DELL TECHNOLOGIES INC. | E26: =VLOOKUP(F26,Department_dim!A$1:B$5,2,FALSE) -> D-104 | F26: Strategy | G26: =VLOOKUP(H26,State_dim!A$1:B$5,2,0) -> S-103 | H26: New York | I26: =VLOOKUP(J26,Payment_dim!A$1:B$6,2,0) -> P-104 | J26: PayPal | K26: 7500 | L26: 1664 | M26: =IFERROR(L26/K26,0) -> 0.22186667
A27: T-125 | B27: 45079 | C27: =VLOOKUP(D27,Client_dim!$A$2:$B$29,2,0) -> C115 | D27: JOHNSON & JOHNSON | E27: =VLOOKUP(F27,Department_dim!A$1:B$5,2,FALSE) -> D-104 | F27: Strategy | G27: =VLOOKUP(H27,State_dim!A$1:B$5,2,0) -> S-103 | H27: New York | I27: =VLOOKUP(J27,Payment_dim!A$1:B$6,2,0) -> P-105 | J27: Transfer | K27: 5500 | L27: 1320 | M27: =IFERROR(L27/K27,0) -> 0.24
A28: T-126 | B28: 45079 | C28: =VLOOKUP(D28,Client_dim!$A$2:$B$29,2,0) -> C111 | D28: FEDEX CORPORATION | E28: =VLOOKUP(F28,Department_dim!A$1:B$5,2,FALSE) -> D-104 | F28: Strategy | G28: =VLOOKUP(H28,State_dim!A$1:B$5,2,0) -> S-103 | H28: New York | I28: =VLOOKUP(J28,Payment_dim!A$1:B$6,2,0) -> P-105 | J28: Transfer | K28: 4625 | L28: 1001 | M28: =IFERROR(L28/K28,0) -> 0.21643243
... A30: T-128 | B30: 45079 | C30: =VLOOKUP(D30,Client_dim!$A$2:$B$29,2,0) -> C117 | D30: LOCKHEED MARTIN CORPORATION | E30: =VLOOKUP(F30,Department_dim!A$1:B$5,2,FALSE) -> D-104 | F30: Strategy | G30: =VLOOKUP(H30,State_dim!A$1:B$5,2,0) -> S-103 | H30: New York | I30: =VLOOKUP(J30,Payment_dim!A$1:B$6,2,0) -> P-101 | J30: Card | K30: 5400 | L30: 540 | M30: =IFERROR(L30/K30,0) -> 0.1

Sheet Data Cleaning 
A1: CS101
A2: Trans_ID | B2: Date | C2: Client | D2: Contacts | E2: Department | F2: State | G2: Payment | H2: Revenue | I2: Profit | J2: Profit Margin
A3: T-101 | B3: 45076 | C3: AMAZON.COM, INC. | D3: Bill Smith | E3: Cloud Tech | F3: Texas | G3: Transfer | H3: 4500 | I3: 598 | J3: =IFERROR(I3/H3,0) -> 0.13288889
A4: T-102 | B4: 45076 | C4: TESLA, INC. | D4: Ken Singh | E4: Strategy | F4: New York | G4: PayPal | H4: 3800 | I4: 1045 | J4: =IFERROR(I4/H4,0) -> 0.275
A5: T-103 | B5: 45076 | C5: NETFLIX, INC. | D5: Harley Fritz | E5: Strategy | F5: New York | G5: Others | H5: 3712.5 | I5: 1009 | J5: =IFERROR(I5/H5,0) -> 0.27178451
A6: T-104 | B6: 45076 | C6: THE PROCTER & GAMBLE COMPANY | D6: Nyla Novak | E6: Operations | F6: Florida | G6: Others | H6: =4994 -> 4994 | I6: 779 | J6: =IFERROR(I6/H6,0) -> 0.15598718
A7: T-105 | B7: 45076 | C7: THE GOLDMAN SACHS GROUP, INC. | D7: David Rasmussen | E7: Operations | F7: Florida | G7: Check | H7: 5000 | I7: 684 | J7: =IFERROR(I7/H7,0) -> 0.1368
A8: T-106 | B8: 45077 | C8: JPMORGAN CHASE & CO. | D8: Ivan Hiney | E8: Cloud Tech | F8: Texas | G8: Transfer | H8: 6100 | I8: 544 | J8: =IFERROR(I8/H8,0) -> 0.089180328
A9: T-107 | B9: 45077 | C9: MORGAN STANLEY | D9: Jonha Ma | E9: Cloud Tech | F9: Texas | G9: Transfer | H9: 4625 | I9: 670 | J9: =IFERROR(I9/H9,0) -> 0.14486486
A10: T-108 | B10: 45077 | C10: CITIGROUP INC. | D10: Jordan Boone | E10: Cloud Tech | F10: Texas | G10: Transfer | H10: =5039 -> 5039 | I10: 2045 | J10: =IFERROR(I10/H10,0) -> 0.40583449
A11: T-109 | B11: 45077 | C11: BANK OF AMERICA CORPORATION | D11: Kylee Townsend | E11: Cloud Tech | F11: Texas | G11: Card | H11: 3600 | I11: 1564 | J11: =IFERROR(I11/H11,0) -> 0.43444444
A12: T-110 | B12: 45077 | C12: WALMART INC. | D12: Nora Rollins | E12: Cloud Tech | F12: Texas | G12: Check | H12: 5100 | I12: 1220 | J12: =IFERROR(I12/H12,0) -> 0.23921569
A13: T-111 | B13: 45077 | C13: TARGET CORPORATION | D13: Brendan Wallace | E13: Cloud Tech | F13: Texas | G13: Check | H13: 4750 | I13: 1435 | J13: =IFERROR(I13/H13,0) -> 0.30210526
A14: T-112 | B14: 45077 | C14: COSTCO WHOLESALE CORPORATION | D14: Conor Wise | E14: Operations | F14: Florida | G14: Transfer | H14: 6000 | I14: 998 | J14: =IFERROR(I14/H14,0) -> 0.16633333
A15: T-113 | B15: 45077 | C15: MCDONALD'S CORPORATION | D15: Steven Michael | E15: Big Data | F15: California | G15: Check | H15: =5039 -> 5039 | I15: 780 | J15: =IFERROR(I15/H15,0) -> 0.15479262
A16: T-114 | B16: 45078 | C16: EXXON MOBIL CORPORATION | D16: Lucia Mckay | E16: Big Data | F16: California | G16: Card | H16: =4994 -> 4994 | I16: 1044 | J16: =IFERROR(I16/H16,0) -> 0.20905086
A17: T-115 | B17: 45078 | C17: VERIZON COMMUNICATIONS INC. | D17: Jose Roach | E17: Big Data | F17: California | G17: Transfer | H17: 3712.5 | I17: 1222 | J17: =IFERROR(I17/H17,0) -> 0.32915825
A18: T-116 | B18: 45078 | C18: THE HOME DEPOT, INC. | D18: Franklin Wrigt | E18: Big Data | F18: California | G18: Transfer | H18: 4950 | I18: 1065 | J18: =IFERROR(I18/H18,0) -> 0.21515152
A19: T-117 | B19: 45078 | C19: CISCO SYSTEMS, INC. | D19: Alia Thornton | E19: Operations | F19: Florida | G19: Transfer | H19: 4750 | I19: 810 | J19: =IFERROR(I19/H19,0) -> 0.17052632
A20: T-118 | B20: 45078 | C20: CHEVRON CORPORATION | D20: Denzel Flores | E20: Operations | F20: Florida | G20: Transfer | H20: 7320 | I20: 933 | J20: =IFERROR(I20/H20,0) -> 0.12745902
A21: T-119 | B21: 45078 | C21: AT&T INC. | D21: Bruno Cordova | E21: Big Data | F21: California | G21: Transfer | H21: 5087.5 | I21: 655 | J21: =IFERROR(I21/H21,0) -> 0.12874693
A22: T-120 | B22: 45078 | C22: INTEL CORPORATION | D22: Jaylynn Napp | E22: Big Data | F22: California | G22: Transfer | H22: 4500 | I22: 722 | J22: =IFERROR(I22/H22,0) -> 0.16044444
A23: T-121 | B23: 45078 | C23: GENERAL MOTORS COMPANY | D23: Bruce Rich | E23: Big Data | F23: California | G23: Card | H23: 4250 | I23: 901 | J23: =IFERROR(I23/H23,0) -> 0.212
A24: T-122 | B24: 45079 | C24: MICROSOFT CORPORATION | D24: Arturo Moore | E24: Big Data | F24: California | G24: PayPal | H24: 5250 | I24: 1349 | J24: =IFERROR(I24/H24,0) -> 0.25695238
A25: T-123 | B25: 45079 | C25: COMCAST CORPORATION | D25: Bryce Carpenter | E25: Strategy | F25: New York | G25: PayPal | H25: 6500 | I25: 1288 | J25: =IFERROR(I25/H25,0) -> 0.19815385
A26: T-124 | B26: 45079 | C26: DELL TECHNOLOGIES INC. | D26: Jaidyn Andersen | E26: Strategy | F26: New York | G26: PayPal | H26: 7500 | I26: 1664 | J26: =IFERROR(I26/H26,0) -> 0.22186667
A27: T-125 | B27: 45079 | C27: JOHNSON & JOHNSON | D27: Mark Walm | E27: Strategy | F27: New York | G27: Transfer | H27: 5500 | I27: 1320 | J27: =IFERROR(I27/H27,0) -> 0.24
A28: T-126 | B28: 45079 | C28: FEDEX CORPORATION | D28: Harry Lee | E28: Strategy | F28: New York | G28: Transfer | H28: 4625 | I28: 1001 | J28: =IFERROR(I28/H28,0) -> 0.21643243
... A30: T-128 | B30: 45079 | C30: LOCKHEED MARTIN CORPORATION | D30: Mik Naam | E30: Strategy | F30: New York | G30: Card | H30: 5400 | I30: 540 | J30: =IFERROR(I30/H30,0) -> 0.1
